parfis/__init__.py
parfis/clib/__init__.py
parfis/clib/datastruct.py
parfis/clib/parfis32.dll
parfis/clib/parfis64.dll
parfis/clib/parfislib.py
parfis/tools/__init__.py
parfis/tools/datafunc.py
parfis-0.0.7.dist-info/METADATA
parfis-0.0.7.dist-info/WHEEL
parfis-0.0.7.dist-info/top_level.txt
parfis-0.0.7.dist-info/RECORD
