Metadata-Version: 2.1
Name: parfis
Version: 0.0.7
Summary: Particles and field simulator
Home-page: UNKNOWN
Author: Ginko Balboa
Author-email: ginkobalboa3@gmail.com
License: UNKNOWN
Project-URL: github, https://github.com/GinkoBalboa/parfis
Project-URL: documentation, https://www.parfis.com
Platform: UNKNOWN
Classifier: Development Status :: 1 - Planning
Classifier: Intended Audience :: Science/Research
Classifier: Programming Language :: Python :: 3.7
Classifier: Programming Language :: Python :: 3.8
Classifier: Programming Language :: Python :: 3.9
Classifier: Programming Language :: Python :: 3.10
Classifier: Programming Language :: C++
Classifier: License :: OSI Approved :: GNU General Public License v3 (GPLv3)
Classifier: Operating System :: Microsoft :: Windows :: Windows 10
Classifier: Operating System :: POSIX :: Linux
Classifier: Topic :: Scientific/Engineering :: Physics
Requires-Python: >=3.7
